Workbook

Sheet Resumen_Cliente
A1: RESUMEN DE OFERTA AL CLIENTE
A3: Servicio a ofertar
A4: Origen
A5: Destino
A6: Tipo de viaje | C6: Sencillo
A7: Kilómetros a recorrer | C7: =Cotizador!B9
A8: Vehículo / configuración | C8: =Cotizador!F4
A9: Días estimados | C9: =Cotizador!B10
A10: PRECIO OFERTA | C10: =Cotizador!B33
A11: Tarifa referencial por km | C11: =Cotizador!B34
A12: Observaciones
A14: Uso: esta hoja está pensada para tomar un screenshot y enviarlo al cliente. Los kilómetros, días, vehículo y precio se alimentan automáticamente desde la hoja Cotizador. Completa manualmente el servicio, origen, destino, tipo de viaje y observaciones.

Sheet Parametros
A1: PARÁMETROS GENERALES DE COSTEO Y OFERTA
A3: Parámetro | B3: Valor | C3: Unidad / aplicación | D3: Fuente / criterio
A4: Margen comercial general | B4: 0.3 | C4: % sobre costo total | D4: Definido por usuario
A5: Depreciación anual | B5: 0.2 | C5: % anual sobre valor total AFT | D5: Definido por usuario
A6: Mantenimiento anual | B6: 0.12 | C6: % anual sobre valor total AFT | D6: Supuesto editable; sustituir por histórico real
A7: Precio combustible | B7: 2.5 | C7: USD/L | D7: Definido por usuario
A8: Lubricantes y grasas | B8: 0.08 | C8: % del costo de combustible | D8: Supuesto editable
A9: Administración / indirectos | B9: 0.1 | C9: % del subtotal operativo | D9: Supuesto editable
A10: Km anuales de referencia | B10: 100000 | C10: km/año por equipo | D10: Base de distribución; editable
A11: Redondeo de oferta | B11: 5 | C11: USD | D11: Redondeo comercial sugerido
A12: Salario diario estándar | B12: 43.15 | C12: USD/trabajador/día | D12: Definido por usuario
A13: Dieta diaria estándar | B13: 5.115 | C13: USD/trabajador/día | D13: Derivado de USD 10.23 para 2 días; editable
A15: Nota: el “margen comercial” se calcula como recargo (markup) sobre el costo total: Precio = Costo × (1 + margen).

Sheet Vehiculos
A1: CATÁLOGO DE VEHÍCULOS / CONFIGURACIONES
A3: ID | B3: Vehículo / configuración | C3: Tipo de servicio | D3: Valor vehículo (USD) | E3: Valor equipo / remolque (USD) | F3: Valor total AFT (USD) | G3: Índice consumo (km/L) | H3: Observaciones
A4: MCV-ACTROS-40 | B4: Cuña MCV Actros C/Semi | C4: Contenedor 40 pies | D4: 139120 | E4: 50689 | F4: =D4+E4 | G4: 2.2 | H4: Configuración inicial aportada por usuario
F5: =IF(COUNTA(D5:E5)=0,"",SUM(D5:E5))
F6: =IF(COUNTA(D6:E6)=0,"",SUM(D6:E6))
F7: =IF(COUNTA(D7:E7)=0,"",SUM(D7:E7))
F8: =IF(COUNTA(D8:E8)=0,"",SUM(D8:E8))
F9: =IF(COUNTA(D9:E9)=0,"",SUM(D9:E9))
F10: =IF(COUNTA(D10:E10)=0,"",SUM(D10:E10))
F11: =IF(COUNTA(D11:E11)=0,"",SUM(D11:E11))
F12: =IF(COUNTA(D12:E12)=0,"",SUM(D12:E12))
F13: =IF(COUNTA(D13:E13)=0,"",SUM(D13:E13))
F14: =IF(COUNTA(D14:E14)=0,"",SUM(D14:E14))
F15: =IF(COUNTA(D15:E15)=0,"",SUM(D15:E15))
F16: =IF(COUNTA(D16:E16)=0,"",SUM(D16:E16))
... F24: =IF(COUNTA(D24:E24)=0,"",SUM(D24:E24))

Sheet Cotizador
A1: COTIZADOR DE SERVICIOS DE TRANSPORTE
A3: DATOS DE LA OFERTA
A4: No. Oferta | D4: Descripción | F4: =IFERROR(VLOOKUP($B$8,Vehiculos!$A$4:$H$24,2,FALSE),"")
A5: Cliente | D5: Tipo de servicio | F5: =IFERROR(VLOOKUP($B$8,Vehiculos!$A$4:$H$24,3,FALSE),"")
A6: Fecha | B6: 46293 | D6: Valor total AFT | F6: =IFERROR(VLOOKUP($B$8,Vehiculos!$A$4:$H$24,6,FALSE),0)
A7: Origen / destino / servicio | D7: Consumo | F7: =IFERROR(VLOOKUP($B$8,Vehiculos!$A$4:$H$24,7,FALSE),0)
A8: ID vehículo / configuración | B8: MCV-ACTROS-40 | D8: Margen aplicado | F8: =IF($B$14="",Parametros!$B$4,$B$14)
A9: Kilómetros totales del servicio | B9: 935
A10: Cantidad de días | B10: 2
A11: Cantidad de trabajadores / choferes | B11: 1
A12: Salario diario por trabajador | B12: =Parametros!$B$12
A13: Dieta diaria por trabajador | B13: =Parametros!$B$13
A14: Margen específico (opcional)
A16: CÁLCULO DEL COSTO DEL SERVICIO
A17: Concepto | B17: Cálculo / base | C17: Costo (USD) | D17: Litros estimados | F17: =IFERROR($B$9/$F$7,0)
A18: Combustible | B18: Km ÷ km/L × precio combustible | C18: =IFERROR($B$9/$F$7*Parametros!$B$7,0) | D18: Depreciación anual AFT | F18: =$F$6*Parametros!$B$5
A19: Salarios | B19: Días × trabajadores × salario diario | C19: =$B$10*$B$11*$B$12 | D19: Depreciación USD/km | F19: =IFERROR(F18/Parametros!$B$10,0)
A20: Dietas | B20: Días × trabajadores × dieta diaria | C20: =$B$10*$B$11*$B$13 | D20: Mantenimiento anual AFT | F20: =$F$6*Parametros!$B$6
A21: Depreciación | B21: AFT × % anual ÷ km/año × km viaje | C21: =$F$6*Parametros!$B$5/Parametros!$B$10*$B$9 | D21: Mantenimiento USD/km | F21: =IFERROR(F20/Parametros!$B$10,0)
A22: Mantenimiento | B22: AFT × % anual ÷ km/año × km viaje | C22: =$F$6*Parametros!$B$6/Parametros!$B$10*$B$9 | D22: Costo total USD/km | F22: =IFERROR($C$26/$B$9,0)
A23: Lubricantes y grasas | B23: % sobre costo combustible | C23: =C18*Parametros!$B$8 | D23: Tarifa ofertada USD/km | F23: =IFERROR($F$25/$B$9,0)
A24: Subtotal operativo | C24: =SUM(C18:C23) | D24: Recargo comercial | F24: =$C$26*$F$8
A25: Administración / indirectos | B25: % sobre subtotal operativo | C25: =C24*Parametros!$B$9 | D25: Precio sin redondear | F25: =$C$26+$F$24
A26: COSTO TOTAL | C26: =C24+C25
A28: RESUMEN DE OFERTA
A29: Costo total estimado | B29: =C26 | D29: Uso: 1) Selecciona el ID del vehículo. 2) Introduce km, días y cantidad de choferes. 3) Ajusta salario/dieta si difieren del estándar. 4) Los porcentajes generales se modifican en “Parametros”. 5) Los 935 km deben representar el recorrido total facturable del equipo.
A30: Margen comercial aplicado | B30: =F8
A31: Ganancia / recargo comercial | B31: =F24
A32: Precio calculado | B32: =F25
A33: PRECIO RECOMENDADO | B33: =IF(Parametros!$B$11<=0,B32,ROUNDUP(B32/Parametros!$B$11,0)*Parametros!$B$11)
A34: Tarifa recomendada por km | B34: =IFERROR(B33/$B$9,0)
